eu_lv_fulltest.py
krangpower/__init__.py
krangpower/_aux_fcn.py
krangpower/_busquery.py
krangpower/_components.py
krangpower/_config_loader.py
krangpower/_deptree.py
krangpower/_edge_tests.py
krangpower/_exceptions.py
krangpower/_graphview.py
krangpower/_krangsuit.py
krangpower/_krg2cdf.py
krangpower/_logging_init.py
krangpower/_method_get.py
krangpower/_nxtable.py
krangpower/_pbar.py
krangpower/_smart_components.py
krangpower/_splash.py
krangpower/aux_fcn.py
krangpower/busquery.py
krangpower/components.py
krangpower/config_loader.py
krangpower/enhancer.py
krangpower/graphview.py
krangpower/krangsuit.py
krangpower/load_dict.py
krangpower/logging_init.py
krangpower/method_get.py
krangpower/nxtable.py
krangpower/pbar.py
krangpower/switchbox.py
krangpower/config/DSSHelp.cfg
krangpower/config/krang_config.cfg
krangpower/defaults/association_types.csv
krangpower/defaults/bypassable_cmd_strings.txt
krangpower/defaults/dangerous_stacks.txt
krangpower/defaults/default_dssentities.json
krangpower/defaults/default_settings.json
krangpower/defaults/error_strings.json
krangpower/defaults/interf_sel.json
krangpower/defaults/interfaces.json
krangpower/defaults/mandatory_unit_dec.json
krangpower/defaults/measurement_units.json
krangpower/defaults/splash.txt
krangpower/defaults/treatments.json
krangpower/enhancer/OpendssdirectEnhancer.py
krangpower/enhancer/__init__.py
krangpower/enhancer/_stdout_hijack.py
krangpower/gv/__init__.py
krangpower/gv/builtingv.py
krangpower/test/eu_lv/eu_lv_load.py
krangpower/test/eu_lv/eu_lv_main.py
krangpower/test/usage_1/us1.py
krangpower-0.2.5.dist-info/METADATA
krangpower-0.2.5.dist-info/RECORD
krangpower-0.2.5.dist-info/WHEEL
krangpower-0.2.5.dist-info/top_level.txt
test/__init__.py
test/eu_lv/__init__.py
test/eu_lv/eu_lv_fulltest.py
test/eu_lv/eu_lv_load.py
test/eu_lv/eu_lv_main.py
test/eu_lv/eu_lv_reload_test.py
test/eu_lv/eulv_maker.py
test/example_smart/__init__.py
test/example_smart/smart_mkt.py
test/usage_1/__init__.py
test/usage_1/us1.py
