Metadata-Version: 2.1
Name: krangpower
Version: 0.2.5
Summary: Distribution System Simulator based on OpenDSS
Home-page: https://krangpower.readthedocs.io
Author: Federico Rosato
Author-email: federico.rosato@supsi.ch
License: MIT
Download-URL: https://github.com/supsi-dacd-isaac/krangpower
Keywords: OpenDSS,pint,DSS
Platform: UNKNOWN
Classifier: Development Status :: 3 - Alpha
Classifier: Intended Audience :: Science/Research
Classifier: Intended Audience :: Education
Classifier: Programming Language :: Python :: 3.5
Classifier: Programming Language :: Python :: 3.6
Classifier: Programming Language :: Python :: 3.7
Provides-Extra: dev
Provides-Extra: extras
Requires-Dist: canonicaljson
Requires-Dist: OpenDSSDirect.py
Requires-Dist: networkx
Requires-Dist: pint
Requires-Dist: numpy
Requires-Dist: pandas
Requires-Dist: scipy
Requires-Dist: matplotlib
Requires-Dist: requests
Requires-Dist: python-dateutil
Requires-Dist: tqdm
Provides-Extra: dev
Provides-Extra: extras
